czlai/__init__.py
czlai/_base_client.py
czlai/_client.py
czlai/_compat.py
czlai/_constants.py
czlai/_exceptions.py
czlai/_files.py
czlai/_models.py
czlai/_qs.py
czlai/_resource.py
czlai/_response.py
czlai/_streaming.py
czlai/_types.py
czlai/_version.py
czlai/py.typed
czlai/_utils/__init__.py
czlai/_utils/_logs.py
czlai/_utils/_proxy.py
czlai/_utils/_reflection.py
czlai/_utils/_streams.py
czlai/_utils/_sync.py
czlai/_utils/_transform.py
czlai/_utils/_typing.py
czlai/_utils/_utils.py
czlai/lib/.keep
czlai/resources/__init__.py
czlai/resources/ai_checkup.py
czlai/resources/ai_conv.py
czlai/resources/ai_memes.py
czlai/resources/ai_trial.py
czlai/resources/ai_trials.py
czlai/resources/aidoc.py
czlai/resources/aidoc_exotic.py
czlai/resources/aipic.py
czlai/resources/aipic_exotics.py
czlai/resources/aipics.py
czlai/resources/buriedpoints.py
czlai/resources/check_points.py
czlai/resources/evaluation.py
czlai/resources/logins.py
czlai/resources/magnum_keys.py
czlai/resources/medical_records.py
czlai/resources/medication_analysis.py
czlai/resources/pet_profiles.py
czlai/resources/point_details.py
czlai/resources/point_prices.py
czlai/resources/point_tasks.py
czlai/resources/policies.py
czlai/resources/session_records.py
czlai/resources/upload.py
czlai/resources/upload_image.py
czlai/resources/upload_image_oss.py
czlai/resources/user_advices.py
czlai/resources/user_points.py
czlai/resources/whitelist.py
czlai/resources/pets/__init__.py
czlai/resources/pets/pet_info.py
czlai/resources/pets/pets.py
czlai/resources/user_module_usages/__init__.py
czlai/resources/user_module_usages/is_add_wecome.py
czlai/resources/user_module_usages/user_module_usages.py
czlai/resources/users/__init__.py
czlai/resources/users/asr.py
czlai/resources/users/contact.py
czlai/resources/users/industry.py
czlai/resources/users/summary.py
czlai/resources/users/user_info.py
czlai/resources/users/users.py
czlai/types/__init__.py
czlai/types/ai_checkup_is_first_params.py
czlai-0.1.0a6.dist-info/METADATA
czlai-0.1.0a6.dist-info/WHEEL
czlai-0.1.0a6.dist-info/licenses/LICENSE
czlai-0.1.0a6.dist-info/RECORD
